README.md
__init__.py
defs.py
instructions.py
zasm.py
zasm-1.0.0.dist-info/LICENSE.txt
zasm-1.0.0.dist-info/METADATA
zasm-1.0.0.dist-info/WHEEL
zasm-1.0.0.dist-info/entry_points.txt
zasm-1.0.0.dist-info/top_level.txt
zasm-1.0.0.dist-info/RECORD
